{
  "metadata": {
    "dataset": "199exam_miniapp_school_filters_sc_cq",
    "version": "2026-05-l2-sc-cq-initial",
    "generated_at": "2026-05-29",
    "source_file": "schoolData/publish/199exam_miniapp_school_publish_sc_cq.json"
  },
  "filters": {
    "program_type": [
      "MPA",
      "MEM",
      "MBA"
    ],
    "province": [
      "四川",
      "重庆",
      "云南",
      "贵州"
    ],
    "city": [
      "凉山彝族自治州",
      "南充",
      "唐山",
      "四川",
      "成都",
      "昆明",
      "泸州",
      "绵阳",
      "贵阳",
      "重庆",
      "雅安"
    ],
    "study_mode": [
      "全日制",
      "非全日制"
    ],
    "school_level_display": [
      "985",
      "211",
      "双非"
    ],
    "tuition_band": [
      "5万以内",
      "5-10万",
      "10-15万",
      "15-25万",
      "25万以上",
      "学费待确认"
    ],
    "score_band": [
      "170以下",
      "170-179",
      "180-189",
      "190-199",
      "200以上",
      "分数线待确认"
    ],
    "filter_tags": [
      "10-15万",
      "15-25万",
      "170-179",
      "170以下",
      "180-189",
      "190-199",
      "200以上",
      "211",
      "25万以上",
      "5-10万",
      "5万以内",
      "985",
      "MBA",
      "MEM",
      "MPA",
      "云南",
      "全日制",
      "凉山彝族自治州",
      "分数线待确认",
      "南充",
      "双非",
      "周末班",
      "唐山",
      "四川",
      "学费待确认",
      "工作日",
      "成都",
      "昆明",
      "泸州",
      "管综",
      "线上",
      "绵阳",
      "贵州",
      "贵阳",
      "重庆",
      "雅安",
      "集中班",
      "非全日制"
    ]
  },
  "sort_order": {
    "program_type": [
      "MPA",
      "MEM",
      "MBA"
    ],
    "province": [
      "四川",
      "重庆",
      "云南",
      "贵州"
    ]
  }
}
