{
  "metadata": {
    "dataset": "party_school_miniapp_publish",
    "generated_at": "2026-05-29",
    "source_dataset": "schoolData/standardized/party/party_school_l1_v2.json",
    "record_count": 8,
    "school_count": 2,
    "program_type": "党校",
    "display_note": "党校 L2 发布层只放前台核心字段；FAQ、特殊政策、历年数据留在 L1/dx_data。"
  },
  "records": [
    {
      "id": "dx-sc-经济学",
      "school_id": "89651",
      "program_id": "dx-sc-经济学",
      "school_name": "中共四川省委党校(四川行政学院)",
      "school_label": "(89651)中共四川省委党校(四川行政学院)",
      "program_type": "党校",
      "degree_type": "单证",
      "exam_type": "免全国联考",
      "province": "四川",
      "city": "成都",
      "school_level_display": "党校",
      "department_label": "在职研究生部",
      "major_category_label": "党校在职研究生",
      "major_label": "经济学",
      "direction": "1.政治经济学 2.产业经济学 3.区域经济学 4.财政学 5.金融学",
      "enrollment": 200,
      "tuition_min": 21600,
      "tuition_max": 21600,
      "duration": 3,
      "study_mode": "非全日制",
      "class_time": "每年集中4次,每次5天,安排在1、2、7、8月",
      "class_location": "成都市青羊区光华村街43号、56号",
      "exam_subjects": "政治理论+经济学专业科目",
      "latest_score": "225(75%)",
      "score_year": 2025,
      "adjustment": "不适用",
      "junior_college_allowed": "否",
      "retired_soldier_plan": "不适用",
      "minority_backbone_plan": "50人",
      "notes": "报考条件：党员要求是；本科；工作满3年。",
      "description": "适合体制内学历硬条件补齐、单位内部认可、低预算在职提升；学信网不可查，需确认本单位认可口径。",
      "admission_analysis": "9.8%(含弃考,2025)；15%(不含弃考,2025口径)",
      "retest_info": "党校自主命题考试，拟录取后按学校要求完成资格审查。",
      "tags": [
        "党校系",
        "四川党校",
        "免联考",
        "单证",
        "低学费",
        "体制内"
      ],
      "filter_tags": [
        "党校系",
        "四川党校",
        "四川",
        "免联考",
        "低预算"
      ],
      "sort_signals": {
        "cost_score": 9,
        "difficulty_score": 6,
        "work_friendly_score": 7,
        "recognition_score": 8
      },
      "publish": {
        "source_record_id": "dx-sc-经济学",
        "source_file": "schoolData/sourceData/party/四川党校在职研究生信息库V2.xlsx",
        "display_scope": "miniapp_l2_core_fields"
      }
    },
    {
      "id": "dx-sc-政治学",
      "school_id": "89651",
      "program_id": "dx-sc-政治学",
      "school_name": "中共四川省委党校(四川行政学院)",
      "school_label": "(89651)中共四川省委党校(四川行政学院)",
      "program_type": "党校",
      "degree_type": "单证",
      "exam_type": "免全国联考",
      "province": "四川",
      "city": "成都",
      "school_level_display": "党校",
      "department_label": "在职研究生部",
      "major_category_label": "党校在职研究生",
      "major_label": "政治学",
      "direction": "1.党史党建 2.政治科学 3.公共管理 4.应急管理 5.马克思主义理论与哲学实践 6.社会治理",
      "enrollment": 300,
      "tuition_min": 21600,
      "tuition_max": 21600,
      "duration": 3,
      "study_mode": "非全日制",
      "class_time": "每年集中4次,每次5天,安排在1、2、7、8月",
      "class_location": "成都市青羊区光华村街43号、56号",
      "exam_subjects": "政治理论+政治学专业科目",
      "latest_score": "180.5(60%)",
      "score_year": 2025,
      "adjustment": "不适用",
      "junior_college_allowed": "否",
      "retired_soldier_plan": "不适用",
      "minority_backbone_plan": "75人",
      "notes": "报考条件：党员要求是；本科；工作满3年。",
      "description": "适合体制内学历硬条件补齐、单位内部认可、低预算在职提升；学信网不可查，需确认本单位认可口径。",
      "admission_analysis": "9.8%(含弃考,2025)；15%(不含弃考,2025口径)",
      "retest_info": "党校自主命题考试，拟录取后按学校要求完成资格审查。",
      "tags": [
        "党校系",
        "四川党校",
        "免联考",
        "单证",
        "低学费",
        "体制内"
      ],
      "filter_tags": [
        "党校系",
        "四川党校",
        "四川",
        "免联考",
        "低预算"
      ],
      "sort_signals": {
        "cost_score": 9,
        "difficulty_score": 6,
        "work_friendly_score": 7,
        "recognition_score": 8
      },
      "publish": {
        "source_record_id": "dx-sc-政治学",
        "source_file": "schoolData/sourceData/party/四川党校在职研究生信息库V2.xlsx",
        "display_scope": "miniapp_l2_core_fields"
      }
    },
    {
      "id": "dx-sc-法学",
      "school_id": "89651",
      "program_id": "dx-sc-法学",
      "school_name": "中共四川省委党校(四川行政学院)",
      "school_label": "(89651)中共四川省委党校(四川行政学院)",
      "program_type": "党校",
      "degree_type": "单证",
      "exam_type": "免全国联考",
      "province": "四川",
      "city": "成都",
      "school_level_display": "党校",
      "department_label": "在职研究生部",
      "major_category_label": "党校在职研究生",
      "major_label": "法学",
      "direction": "1.法理学+党内法规 2.行政法学+法治政府建设 3.民商法学+法治社会",
      "enrollment": 100,
      "tuition_min": 21600,
      "tuition_max": 21600,
      "duration": 3,
      "study_mode": "非全日制",
      "class_time": "每年集中4次,每次5天,安排在1、2、7、8月",
      "class_location": "成都市青羊区光华村街43号、56号",
      "exam_subjects": "政治理论+法学专业科目",
      "latest_score": "184(61%)",
      "score_year": 2025,
      "adjustment": "不适用",
      "junior_college_allowed": "否",
      "retired_soldier_plan": "不适用",
      "minority_backbone_plan": "25人",
      "notes": "报考条件：党员要求是；本科；工作满3年。",
      "description": "适合体制内学历硬条件补齐、单位内部认可、低预算在职提升；学信网不可查，需确认本单位认可口径。",
      "admission_analysis": "9.8%(含弃考,2025)；15%(不含弃考,2025口径)",
      "retest_info": "党校自主命题考试，拟录取后按学校要求完成资格审查。",
      "tags": [
        "党校系",
        "四川党校",
        "免联考",
        "单证",
        "低学费",
        "体制内"
      ],
      "filter_tags": [
        "党校系",
        "四川党校",
        "四川",
        "免联考",
        "低预算"
      ],
      "sort_signals": {
        "cost_score": 9,
        "difficulty_score": 6,
        "work_friendly_score": 7,
        "recognition_score": 8
      },
      "publish": {
        "source_record_id": "dx-sc-法学",
        "source_file": "schoolData/sourceData/party/四川党校在职研究生信息库V2.xlsx",
        "display_scope": "miniapp_l2_core_fields"
      }
    },
    {
      "id": "dx-cq-经济管理",
      "school_id": "89650",
      "program_id": "dx-cq-经济管理",
      "school_name": "中共重庆市委党校(重庆行政学院)",
      "school_label": "(89650)中共重庆市委党校(重庆行政学院)",
      "program_type": "党校",
      "degree_type": "单证",
      "exam_type": "免全国联考",
      "province": "重庆",
      "city": "重庆",
      "school_level_display": "党校",
      "department_label": "在职研究生部",
      "major_category_label": "党校在职研究生",
      "major_label": "经济管理",
      "direction": "政治理论+专业综合(政治经济学、管理学)",
      "enrollment": 200,
      "tuition_min": 24000,
      "tuition_max": 24000,
      "duration": 3,
      "study_mode": "非全日制",
      "class_time": "每月集中1次,每次3天左右(含周末),寒暑假不上课",
      "class_location": "重庆市九龙坡区渝州路132号",
      "exam_subjects": "政治理论+专业综合(政治经济学、管理学)",
      "latest_score": "195(65%)",
      "score_year": 2025,
      "adjustment": "不适用",
      "junior_college_allowed": "否",
      "retired_soldier_plan": "不适用",
      "minority_backbone_plan": "不适用",
      "notes": "报考条件：党员要求否；本科；工作满2年。",
      "description": "适合体制内学历硬条件补齐、单位内部认可、低预算在职提升；学信网不可查，需确认本单位认可口径。",
      "admission_analysis": "13.5%(含弃考,2025)；22.5%(不含弃考,2025口径)",
      "retest_info": "党校自主命题考试，拟录取后按学校要求完成资格审查。",
      "tags": [
        "党校系",
        "重庆党校",
        "免联考",
        "单证",
        "低学费",
        "体制内"
      ],
      "filter_tags": [
        "党校系",
        "重庆党校",
        "重庆",
        "免联考",
        "低预算"
      ],
      "sort_signals": {
        "cost_score": 9,
        "difficulty_score": 5,
        "work_friendly_score": 8,
        "recognition_score": 8
      },
      "publish": {
        "source_record_id": "dx-cq-经济管理",
        "source_file": "schoolData/sourceData/party/重庆党校在职研究生信息库V2.xlsx",
        "display_scope": "miniapp_l2_core_fields"
      }
    },
    {
      "id": "dx-cq-法律",
      "school_id": "89650",
      "program_id": "dx-cq-法律",
      "school_name": "中共重庆市委党校(重庆行政学院)",
      "school_label": "(89650)中共重庆市委党校(重庆行政学院)",
      "program_type": "党校",
      "degree_type": "单证",
      "exam_type": "免全国联考",
      "province": "重庆",
      "city": "重庆",
      "school_level_display": "党校",
      "department_label": "在职研究生部",
      "major_category_label": "党校在职研究生",
      "major_label": "法律",
      "direction": "政治理论+专业综合(法理学、行政法与行政诉讼法)",
      "enrollment": 200,
      "tuition_min": 24000,
      "tuition_max": 24000,
      "duration": 3,
      "study_mode": "非全日制",
      "class_time": "每月集中1次,每次3天左右(含周末),寒暑假不上课",
      "class_location": "重庆市九龙坡区渝州路132号",
      "exam_subjects": "政治理论+专业综合(法理学、行政法与行政诉讼法)",
      "latest_score": "193(64%)",
      "score_year": 2025,
      "adjustment": "不适用",
      "junior_college_allowed": "否",
      "retired_soldier_plan": "不适用",
      "minority_backbone_plan": "不适用",
      "notes": "报考条件：党员要求否；本科；工作满2年。",
      "description": "适合体制内学历硬条件补齐、单位内部认可、低预算在职提升；学信网不可查，需确认本单位认可口径。",
      "admission_analysis": "13.5%(含弃考,2025)；22.5%(不含弃考,2025口径)",
      "retest_info": "党校自主命题考试，拟录取后按学校要求完成资格审查。",
      "tags": [
        "党校系",
        "重庆党校",
        "免联考",
        "单证",
        "低学费",
        "体制内"
      ],
      "filter_tags": [
        "党校系",
        "重庆党校",
        "重庆",
        "免联考",
        "低预算"
      ],
      "sort_signals": {
        "cost_score": 9,
        "difficulty_score": 5,
        "work_friendly_score": 8,
        "recognition_score": 8
      },
      "publish": {
        "source_record_id": "dx-cq-法律",
        "source_file": "schoolData/sourceData/party/重庆党校在职研究生信息库V2.xlsx",
        "display_scope": "miniapp_l2_core_fields"
      }
    },
    {
      "id": "dx-cq-公共管理",
      "school_id": "89650",
      "program_id": "dx-cq-公共管理",
      "school_name": "中共重庆市委党校(重庆行政学院)",
      "school_label": "(89650)中共重庆市委党校(重庆行政学院)",
      "program_type": "党校",
      "degree_type": "单证",
      "exam_type": "免全国联考",
      "province": "重庆",
      "city": "重庆",
      "school_level_display": "党校",
      "department_label": "在职研究生部",
      "major_category_label": "党校在职研究生",
      "major_label": "公共管理",
      "direction": "政治理论+专业综合(政治学、公共管理学)",
      "enrollment": 170,
      "tuition_min": 24000,
      "tuition_max": 24000,
      "duration": 3,
      "study_mode": "非全日制",
      "class_time": "每月集中1次,每次3天左右(含周末),寒暑假不上课",
      "class_location": "重庆市九龙坡区渝州路132号",
      "exam_subjects": "政治理论+专业综合(政治学、公共管理学)",
      "latest_score": "186(62%)",
      "score_year": 2025,
      "adjustment": "不适用",
      "junior_college_allowed": "否",
      "retired_soldier_plan": "不适用",
      "minority_backbone_plan": "不适用",
      "notes": "报考条件：党员要求否；本科；工作满2年。",
      "description": "适合体制内学历硬条件补齐、单位内部认可、低预算在职提升；学信网不可查，需确认本单位认可口径。",
      "admission_analysis": "13.5%(含弃考,2025)；22.5%(不含弃考,2025口径)",
      "retest_info": "党校自主命题考试，拟录取后按学校要求完成资格审查。",
      "tags": [
        "党校系",
        "重庆党校",
        "免联考",
        "单证",
        "低学费",
        "体制内"
      ],
      "filter_tags": [
        "党校系",
        "重庆党校",
        "重庆",
        "免联考",
        "低预算"
      ],
      "sort_signals": {
        "cost_score": 9,
        "difficulty_score": 5,
        "work_friendly_score": 8,
        "recognition_score": 8
      },
      "publish": {
        "source_record_id": "dx-cq-公共管理",
        "source_file": "schoolData/sourceData/party/重庆党校在职研究生信息库V2.xlsx",
        "display_scope": "miniapp_l2_core_fields"
      }
    },
    {
      "id": "dx-cq-党政管理",
      "school_id": "89650",
      "program_id": "dx-cq-党政管理",
      "school_name": "中共重庆市委党校(重庆行政学院)",
      "school_label": "(89650)中共重庆市委党校(重庆行政学院)",
      "program_type": "党校",
      "degree_type": "单证",
      "exam_type": "免全国联考",
      "province": "重庆",
      "city": "重庆",
      "school_level_display": "党校",
      "department_label": "在职研究生部",
      "major_category_label": "党校在职研究生",
      "major_label": "党政管理",
      "direction": "政治理论+专业综合(政治学、马克思主义党的学说史)",
      "enrollment": 170,
      "tuition_min": 24000,
      "tuition_max": 24000,
      "duration": 3,
      "study_mode": "非全日制",
      "class_time": "每月集中1次,每次3天左右(含周末),寒暑假不上课",
      "class_location": "重庆市九龙坡区渝州路132号",
      "exam_subjects": "政治理论+专业综合(政治学、马克思主义党的学说史)",
      "latest_score": "199(66%)",
      "score_year": 2025,
      "adjustment": "不适用",
      "junior_college_allowed": "否",
      "retired_soldier_plan": "不适用",
      "minority_backbone_plan": "不适用",
      "notes": "报考条件：党员要求否；本科；工作满2年。",
      "description": "适合体制内学历硬条件补齐、单位内部认可、低预算在职提升；学信网不可查，需确认本单位认可口径。",
      "admission_analysis": "13.5%(含弃考,2025)；22.5%(不含弃考,2025口径)",
      "retest_info": "党校自主命题考试，拟录取后按学校要求完成资格审查。",
      "tags": [
        "党校系",
        "重庆党校",
        "免联考",
        "单证",
        "低学费",
        "体制内"
      ],
      "filter_tags": [
        "党校系",
        "重庆党校",
        "重庆",
        "免联考",
        "低预算"
      ],
      "sort_signals": {
        "cost_score": 9,
        "difficulty_score": 5,
        "work_friendly_score": 8,
        "recognition_score": 8
      },
      "publish": {
        "source_record_id": "dx-cq-党政管理",
        "source_file": "schoolData/sourceData/party/重庆党校在职研究生信息库V2.xlsx",
        "display_scope": "miniapp_l2_core_fields"
      }
    },
    {
      "id": "dx-cq-战略管理",
      "school_id": "89650",
      "program_id": "dx-cq-战略管理",
      "school_name": "中共重庆市委党校(重庆行政学院)",
      "school_label": "(89650)中共重庆市委党校(重庆行政学院)",
      "program_type": "党校",
      "degree_type": "单证",
      "exam_type": "免全国联考",
      "province": "重庆",
      "city": "重庆",
      "school_level_display": "党校",
      "department_label": "在职研究生部",
      "major_category_label": "党校在职研究生",
      "major_label": "战略管理",
      "direction": "政治理论+专业综合(领导科学、战略思维)",
      "enrollment": 160,
      "tuition_min": 24000,
      "tuition_max": 24000,
      "duration": 3,
      "study_mode": "非全日制",
      "class_time": "每月集中1次,每次3天左右(含周末),寒暑假不上课",
      "class_location": "重庆市九龙坡区渝州路132号",
      "exam_subjects": "政治理论+专业综合(领导科学、战略思维)",
      "latest_score": "200(67%)",
      "score_year": 2025,
      "adjustment": "不适用",
      "junior_college_allowed": "否",
      "retired_soldier_plan": "不适用",
      "minority_backbone_plan": "不适用",
      "notes": "报考条件：党员要求否；本科；工作满2年。",
      "description": "适合体制内学历硬条件补齐、单位内部认可、低预算在职提升；学信网不可查，需确认本单位认可口径。",
      "admission_analysis": "13.5%(含弃考,2025)；22.5%(不含弃考,2025口径)",
      "retest_info": "党校自主命题考试，拟录取后按学校要求完成资格审查。",
      "tags": [
        "党校系",
        "重庆党校",
        "免联考",
        "单证",
        "低学费",
        "体制内"
      ],
      "filter_tags": [
        "党校系",
        "重庆党校",
        "重庆",
        "免联考",
        "低预算"
      ],
      "sort_signals": {
        "cost_score": 9,
        "difficulty_score": 5,
        "work_friendly_score": 8,
        "recognition_score": 8
      },
      "publish": {
        "source_record_id": "dx-cq-战略管理",
        "source_file": "schoolData/sourceData/party/重庆党校在职研究生信息库V2.xlsx",
        "display_scope": "miniapp_l2_core_fields"
      }
    }
  ]
}
